pypi_attestation_models/__init__.py
pypi_attestation_models/_impl.py
pypi_attestation_models/py.typed
pypi_attestation_models-0.0.5.dist-info/LICENSE
pypi_attestation_models-0.0.5.dist-info/WHEEL
pypi_attestation_models-0.0.5.dist-info/METADATA
pypi_attestation_models-0.0.5.dist-info/RECORD
