Metadata-Version: 2.1
Name: pypi-attestation-models
Version: 0.0.5
Summary: A library to convert between Sigstore Bundles and PEP-740 Attestation objects
Author-email: Trail of Bits <opensource@trailofbits.com>
Requires-Python: >=3.9
Classifier: Programming Language :: Python :: 3
Classifier: License :: OSI Approved :: Apache Software License
Requires-Dist: cryptography
Requires-Dist: packaging
Requires-Dist: pydantic
Requires-Dist: sigstore~=3.0.0
Requires-Dist: sigstore-protobuf-specs
Requires-Dist: pypi-attestation-models[doc,test,lint] ; extra == "dev"
Requires-Dist: twine ; extra == "dev"
Requires-Dist: wheel ; extra == "dev"
Requires-Dist: build ; extra == "dev"
Requires-Dist: pdoc ; extra == "doc"
Requires-Dist: ruff ~= 0.2 ; extra == "lint"
Requires-Dist: mypy >= 1.0 ; extra == "lint"
Requires-Dist: types-html5lib ; extra == "lint"
Requires-Dist: types-requests ; extra == "lint"
Requires-Dist: types-toml ; extra == "lint"
Requires-Dist: interrogate ; extra == "lint"
Requires-Dist: pytest ; extra == "test"
Requires-Dist: pytest-cov ; extra == "test"
Requires-Dist: pretend ; extra == "test"
Requires-Dist: coverage[toml] ; extra == "test"
Project-URL: Documentation, https://trailofbits.github.io/pypi-attestation-models/
Project-URL: Homepage, https://pypi.org/project/pypi-attestation-models
Project-URL: Issues, https://github.com/trailofbits/pypi-attestation-models/issues
Project-URL: Source, https://github.com/trailofbits/pypi-attestation-models
Provides-Extra: dev
Provides-Extra: doc
Provides-Extra: lint
Provides-Extra: test
